<?xml version="1.0" encoding="utf-8" ?><dwsync><file name="admin_backup_menu.tpl" server="en-obra.com.co/public_html/" local="3515501379" remote="318763443834744912" Dst="-1" /><file name="admin_banners_swf.tpl" server="en-obra.com.co/public_html/" local="3515501379" remote="318763443834744912" Dst="-1" /><file name="admin_banners_types_menu.tpl" server="en-obra.com.co/public_html/" local="3515501381" remote="318763443834744912" Dst="-1" /><file name="admin_blog_menu.tpl" server="en-obra.com.co/public_html/" local="3515501381" remote="318763443834744912" Dst="-1" /><file name="admin_categories_menu.tpl" server="en-obra.com.co/public_html/" local="3515501381" remote="318763443859628112" Dst="-1" /><file name="admin_content_page.tpl" server="en-obra.com.co/public_html/" local="3515501382" remote="318763443834744912" Dst="-1" /><file name="admin_discount_codes_menu.tpl" server="en-obra.com.co/public_html/" local="3515501382" remote="318763443834744912" Dst="-1" /><file name="admin_debug.tpl" server="en-obra.com.co/public_html/" local="3515501382" remote="318763443834744912" Dst="-1" /><file name="admin_email_campaigns_variables_menu.tpl" server="en-obra.com.co/public_html/" local="3515501384" remote="318763443834744912" Dst="-1" /><file name="admin_email_log_email.tpl" server="en-obra.com.co/public_html/" local="3515501384" remote="318763443834744912" Dst="-1" /><file name="admin_email_menu.tpl" server="en-obra.com.co/public_html/" local="3515501384" remote="318763443834744912" Dst="-1" /><file name="admin_email_queue_email.tpl" server="en-obra.com.co/public_html/" local="3515501385" remote="318763443834744912" Dst="-1" /><file name="admin_email_templates_menu.tpl" server="en-obra.com.co/public_html/" local="3515501385" remote="318763443834744912" Dst="-1" /><file name="admin_email_templates_variables.tpl" server="en-obra.com.co/public_html/" local="3515501385" remote="318763443834744912" Dst="-1" /><file name="admin_faq_menu.tpl" server="en-obra.com.co/public_html/" local="3515501386" remote="318763443834744912" Dst="-1" /><file name="admin_feeds_external_menu.tpl" server="en-obra.com.co/public_html/" local="3515501386" remote="318763443834744912" Dst="-1" /><file name="admin_fields_menu.tpl" server="en-obra.com.co/public_html/" local="3515501386" remote="318763443834744912" Dst="-1" /><file name="admin_form.tpl" server="en-obra.com.co/public_html/" local="3515501388" remote="318763443834744912" Dst="-1" /><file name="admin_form_checkbox.tpl" server="en-obra.com.co/public_html/" local="3515501388" remote="318763443834744912" Dst="-1" /><file name="admin_form_checkbox_wrapper.tpl" server="en-obra.com.co/public_html/" local="3515501388" remote="318763443834744912" Dst="-1" /><file name="admin_form_color.tpl" server="en-obra.com.co/public_html/" local="3515501389" remote="318763443859628112" Dst="-1" /><file name="admin_form_coordinates_link.tpl" server="en-obra.com.co/public_html/" local="3515501389" remote="318763443834744912" Dst="-1" /><file name="admin_form_counter.tpl" server="en-obra.com.co/public_html/" local="3515501389" remote="318763443859628112" Dst="-1" /><file name="admin_form_currency.tpl" server="en-obra.com.co/public_html/" local="3515501390" remote="318763443859628112" Dst="-1" /><file name="admin_form_custom.tpl" server="en-obra.com.co/public_html/" local="3515501390" remote="318763443859628112" Dst="-1" /><file name="admin_form_date.tpl" server="en-obra.com.co/public_html/" local="3515501390" remote="318763443859628112" Dst="-1" /><file name="admin_form_datetime.tpl" server="en-obra.com.co/public_html/" local="3515501392" remote="318763443859628112" Dst="-1" /><file name="admin_form_field_label.tpl" server="en-obra.com.co/public_html/" local="3515501392" remote="318763443834744912" Dst="-1" /><file name="admin_form_field.tpl" server="en-obra.com.co/public_html/" local="3515501392" remote="318763443834744912" Dst="-1" /><file name="admin_form_fieldset.tpl" server="en-obra.com.co/public_html/" local="3515501394" remote="318763443834744912" Dst="-1" /><file name="admin_form_fieldset_help.tpl" server="en-obra.com.co/public_html/" local="3515501394" remote="318763443834744912" Dst="-1" /><file name="admin_form_file.tpl" server="en-obra.com.co/public_html/" local="3515501394" remote="318763443859628112" Dst="-1" /><file name="admin_form_file_multiple.tpl" server="en-obra.com.co/public_html/" local="3515501395" remote="318763443834744912" Dst="-1" /><file name="admin_form_hours.tpl" server="en-obra.com.co/public_html/" local="3515501395" remote="318763443859628112" Dst="-1" /><file name="admin_form_hours_selected.tpl" server="en-obra.com.co/public_html/" local="3515501395" remote="318763443859628112" Dst="-1" /><file name="admin_form_htmleditor.tpl" server="en-obra.com.co/public_html/" local="3515501396" remote="318763443859628112" Dst="-1" /><file name="admin_form_password.tpl" server="en-obra.com.co/public_html/" local="3515501396" remote="318763443859628112" Dst="-1" /><file name="admin_form_radio.tpl" server="en-obra.com.co/public_html/" local="3515501396" remote="318763443859628112" Dst="-1" /><file name="admin_form_radio_wrapper.tpl" server="en-obra.com.co/public_html/" local="3515501398" remote="318763443834744912" Dst="-1" /><file name="admin_form_readonly.tpl" server="en-obra.com.co/public_html/" local="3515501398" remote="318763443859628112" Dst="-1" /><file name="admin_form_select.tpl" server="en-obra.com.co/public_html/" local="3515501398" remote="318763443859628112" Dst="-1" /><file name="admin_form_select_cascading.tpl" server="en-obra.com.co/public_html/" local="3515501399" remote="318763443859628112" Dst="-1" /><file name="admin_form_select_cascading_selected.tpl" server="en-obra.com.co/public_html/" local="3515501399" remote="318763443859628112" Dst="-1" /><file name="admin_form_select_multiple.tpl" server="en-obra.com.co/public_html/" local="3515501399" remote="318763443859628112" Dst="-1" /><file name="admin_form_select_multiple_tree.tpl" server="en-obra.com.co/public_html/" local="3515501400" remote="318763443859628112" Dst="-1" /><file name="admin_form_select_tree.tpl" server="en-obra.com.co/public_html/" local="3515501400" remote="318763443859628112" Dst="-1" /><file name="admin_form_select_tree_expanding.tpl" server="en-obra.com.co/public_html/" local="3515501400" remote="318763443859628112" Dst="-1" /><file name="admin_form_select_window.tpl" server="en-obra.com.co/public_html/" local="3515501402" remote="318763443834744912" Dst="-1" /><file name="admin_form_stars.tpl" server="en-obra.com.co/public_html/" local="3515501402" remote="318763443859628112" Dst="-1" /><file name="admin_form_submit.tpl" server="en-obra.com.co/public_html/" local="3515501402" remote="318763443859628112" Dst="-1" /><file name="admin_form_submit_image.tpl" server="en-obra.com.co/public_html/" local="3515501403" remote="318763443859628112" Dst="-1" /><file name="admin_form_text.tpl" server="en-obra.com.co/public_html/" local="3515501403" remote="318763443859628112" Dst="-1" /><file name="admin_form_text_autocomplete.tpl" server="en-obra.com.co/public_html/" local="3515501403" remote="318763443859628112" Dst="-1" /><file name="admin_form_textarea.tpl" server="en-obra.com.co/public_html/" local="3515501405" remote="318763443859628112" Dst="-1" /><file name="admin_generic_menu.tpl" server="en-obra.com.co/public_html/" local="3515501405" remote="318763443834744912" Dst="-1" /><file name="admin_imports_menu.tpl" server="en-obra.com.co/public_html/" local="3515501405" remote="318763443834744912" Dst="-1" /><file name="admin_index_information_menu.tpl" server="en-obra.com.co/public_html/" local="3515501406" remote="318763443859628112" Dst="-1" /><file name="admin_invoices_menu.tpl" server="en-obra.com.co/public_html/" local="3515501406" remote="318763443859628112" Dst="-1" /><file name="admin_index_menu.tpl" server="en-obra.com.co/public_html/" local="3515501406" remote="318763443834744912" Dst="-1" /><file name="admin_languages_menu.tpl" server="en-obra.com.co/public_html/" local="3515501407" remote="318763443834744912" Dst="-1" /><file name="admin_link_checker_menu.tpl" server="en-obra.com.co/public_html/" local="3515501407" remote="318763443834744912" Dst="-1" /><file name="admin_listing_header.tpl" server="en-obra.com.co/public_html/" local="3515501407" remote="318763443859628112" Dst="-1" /><file name="admin_listings_menu.tpl" server="en-obra.com.co/public_html/" local="3515501409" remote="318763443834744912" Dst="-1" /><file name="admin_listings_view_menu.tpl" server="en-obra.com.co/public_html/" local="3515501409" remote="318763443834744912" Dst="-1" /><file name="admin_locations_menu.tpl" server="en-obra.com.co/public_html/" local="3515501409" remote="318763443859628112" Dst="-1" /><file name="admin_log_menu.tpl" server="en-obra.com.co/public_html/" local="3515501410" remote="318763443834744912" Dst="-1" /><file name="admin_mail_menu.tpl" server="en-obra.com.co/public_html/" local="3515501410" remote="318763443834744912" Dst="-1" /><file name="admin_mail_templates_menu.tpl" server="en-obra.com.co/public_html/" local="3515501410" remote="318763443834744912" Dst="-1" /><file name="admin_maintenance_menu.tpl" server="en-obra.com.co/public_html/" local="3515501411" remote="318763443859628112" Dst="-1" /><file name="admin_message.tpl" server="en-obra.com.co/public_html/" local="3515501411" remote="318763443834744912" Dst="-1" /><file name="admin_orders_menu.tpl" server="en-obra.com.co/public_html/" local="3515501411" remote="318763443834744912" Dst="-1" /><file name="admin_page_navigation.tpl" server="en-obra.com.co/public_html/" local="3515501412" remote="318763443834744912" Dst="-1" /><file name="admin_page_select.tpl" server="en-obra.com.co/public_html/" local="3515501413" remote="318763443834744912" Dst="-1" /><file name="admin_pages_menu.tpl" server="en-obra.com.co/public_html/" local="3515501413" remote="318763443834744912" Dst="-1" /><file name="admin_payment_gateways_menu.tpl" server="en-obra.com.co/public_html/" local="3515501414" remote="318763443834744912" Dst="-1" /><file name="admin_plugins_menu.tpl" server="en-obra.com.co/public_html/" local="3515501414" remote="318763443834744912" Dst="-1" /><file name="admin_products_menu.tpl" server="en-obra.com.co/public_html/" local="3515501414" remote="318763443859628112" Dst="-1" /><file name="admin_quick_search.tpl" server="en-obra.com.co/public_html/" local="3515501416" remote="318763443859628112" Dst="-1" /><file name="admin_reviews_menu.tpl" server="en-obra.com.co/public_html/" local="3515501416" remote="318763443834744912" Dst="-1" /><file name="admin_search_log_menu.tpl" server="en-obra.com.co/public_html/" local="3515501416" remote="318763443859628112" Dst="-1" /><file name="admin_settings_banners.tpl" server="en-obra.com.co/public_html/" local="3515501416" remote="318763443834744912" Dst="-1" /><file name="admin_settings_blog.tpl" server="en-obra.com.co/public_html/" local="3515501417" remote="318763443859628112" Dst="-1" /><file name="admin_settings_caching.tpl" server="en-obra.com.co/public_html/" local="3515501417" remote="318763443834744912" Dst="-1" /><file name="admin_settings_categories.tpl" server="en-obra.com.co/public_html/" local="3515501418" remote="318763443834744912" Dst="-1" /><file name="admin_settings_classifieds.tpl" server="en-obra.com.co/public_html/" local="3515501418" remote="318763443834744912" Dst="-1" /><file name="admin_settings_custom.tpl" server="en-obra.com.co/public_html/" local="3515501418" remote="318763443834744912" Dst="-1" /><file name="admin_settings_custom_menu.tpl" server="en-obra.com.co/public_html/" local="3515501419" remote="318763443834744912" Dst="-1" /><file name="admin_settings_documents.tpl" server="en-obra.com.co/public_html/" local="3515501419" remote="318763443834744912" Dst="-1" /><file name="admin_settings_email.tpl" server="en-obra.com.co/public_html/" local="3515501419" remote="318763443859628112" Dst="-1" /><file name="admin_settings_gallery.tpl" server="en-obra.com.co/public_html/" local="3515501421" remote="318763443859628112" Dst="-1" /><file name="admin_settings_general.tpl" server="en-obra.com.co/public_html/" local="3515501421" remote="318763443859628112" Dst="-1" /><file name="admin_settings_invoicing.tpl" server="en-obra.com.co/public_html/" local="3515501421" remote="318763443859628112" Dst="-1" /><file name="admin_settings_listings.tpl" server="en-obra.com.co/public_html/" local="3515501422" remote="318763443859628112" Dst="-1" /><file name="admin_settings_locations.tpl" server="en-obra.com.co/public_html/" local="3515501422" remote="318763443834744912" Dst="-1" /><file name="admin_settings_logos.tpl" server="en-obra.com.co/public_html/" local="3515501422" remote="318763443834744912" Dst="-1" /><file name="admin_settings_menu.tpl" server="en-obra.com.co/public_html/" local="3515501423" remote="318763443834744912" Dst="-1" /><file name="admin_settings_offers.tpl" server="en-obra.com.co/public_html/" local="3515501423" remote="318763443834744912" Dst="-1" /><file name="admin_settings_other.tpl" server="en-obra.com.co/public_html/" local="3515501423" remote="318763443859628112" Dst="-1" /><file name="admin_settings_reviews.tpl" server="en-obra.com.co/public_html/" local="3515501425" remote="318763443834744912" Dst="-1" /><file name="admin_settings_search.tpl" server="en-obra.com.co/public_html/" local="3515501425" remote="318763443859628112" Dst="-1" /><file name="admin_settings_sideboxes.tpl" server="en-obra.com.co/public_html/" local="3515501425" remote="318763443834744912" Dst="-1" /><file name="admin_settings_users.tpl" server="en-obra.com.co/public_html/" local="3515501426" remote="318763443859628112" Dst="-1" /><file name="admin_settings_website_screenshots.tpl" server="en-obra.com.co/public_html/" local="3515501426" remote="318763443834744912" Dst="-1" /><file name="admin_side_menu_box.tpl" server="en-obra.com.co/public_html/" local="3515501426" remote="318763443834744912" Dst="-1" /><file name="admin_site_links_menu.tpl" server="en-obra.com.co/public_html/" local="3515501427" remote="318763443834744912" Dst="-1" /><file name="admin_table_list.tpl" server="en-obra.com.co/public_html/" local="3515501427" remote="318763443859628112" Dst="-1" /><file name="admin_tax_menu.tpl" server="en-obra.com.co/public_html/" local="3515501427" remote="318763443834744912" Dst="-1" /><file name="admin_templates_menu.tpl" server="en-obra.com.co/public_html/" local="3515501429" remote="318763443834744912" Dst="-1" /><file name="admin_users_menu.tpl" server="en-obra.com.co/public_html/" local="3515501429" remote="318763443859628112" Dst="-1" /><file name="admin_users_summary_header.tpl" server="en-obra.com.co/public_html/" local="3515501429" remote="318763443834744912" Dst="-1" /><file name="admin_zip_codes_menu.tpl" server="en-obra.com.co/public_html/" local="3515501430" remote="318763443834744912" Dst="-1" /></dwsync>